cpost/__init__.py
cpost/_b2c.py
cpost/_db.py
cpost/api.py
cpost/db.py
cpost/data/data.db
cpost-0.0.6.dist-info/LICENSE
cpost-0.0.6.dist-info/METADATA
cpost-0.0.6.dist-info/WHEEL
cpost-0.0.6.dist-info/top_level.txt
cpost-0.0.6.dist-info/RECORD
